alidaargparser/__init__.py
alidaargparser/assets_utils.py
alidaargparser/dataset.py
alidaargparser/generator.py
alidaargparser/map.py
alidaargparser/model.py
alidaargparser/parser.py
alidaargparser/port.py
alidaargparser/property.py
alidaargparser/translation_dictionary.py
alidaargparser/type_utils.py
alidaargparser/templates/__init__.py
alidaargparser/templates/spark_3_2_0.py
alidaargparser/templates/template.py
alida_arg_parser-0.2.4.dist-info/METADATA
alida_arg_parser-0.2.4.dist-info/WHEEL
alida_arg_parser-0.2.4.dist-info/top_level.txt
alida_arg_parser-0.2.4.dist-info/RECORD
