Metadata-Version: 2.1
Name: alida-arg-parser
Version: 0.2.4
Summary: Python argparser modified for Alida services
Home-page: UNKNOWN
Author: Alida research team
Author-email: salvatore.cipolla@eng.it
License: UNKNOWN
Platform: UNKNOWN
Classifier: Programming Language :: Python :: 3
Classifier: License :: OSI Approved :: MIT License
Classifier: Operating System :: OS Independent
Requires-Python: >=3.6
Requires-Dist: jinja2 (>=2.10)
Requires-Dist: yaml
